NanoJson/__init__.py
nanojson-1.3.dist-info/licenses/LICENSE.txt
nanojson-1.3.dist-info/METADATA
nanojson-1.3.dist-info/WHEEL
nanojson-1.3.dist-info/top_level.txt
nanojson-1.3.dist-info/RECORD
