Metadata-Version: 2.4
Name: NanoJson
Version: 1.3
Summary: A simple, efficient, and feature-rich Python library for working with JSON files.
Home-page: https://t.me/midoghanam
Author: CodeDev Company
Author-email: CodeDev Company <codedev.eg@hotmain.com>, Mohamed Ahmed Ghanam <mghanam883@outlook.com>
License: MIT
Project-URL: Homepage, https://t.me/mido_ghanam
Project-URL: EgyptianProgrammers, https://t.me/egyptionprogrammers
Project-URL: SecoundTelegramChannel, https://t.me/mido_team
Project-URL: TelegramAccount, https://t.me/midoghanam
Project-URL: Whatsapp, https://wa.me/201101023681
Keywords: JSON,Python,library
Requires-Python: >=3.6
License-File: LICENSE.txt
Dynamic: author
Dynamic: home-page
Dynamic: license-file
Dynamic: requires-python
